DebugLibrary/__init__.py
DebugLibrary/cmdcompleter.py
DebugLibrary/debugcmd.py
DebugLibrary/globals.py
DebugLibrary/keywords.py
DebugLibrary/prompttoolkitcmd.py
DebugLibrary/robotapp.py
DebugLibrary/robotkeyword.py
DebugLibrary/robotlib.py
DebugLibrary/robotselenium.py
DebugLibrary/robotvar.py
DebugLibrary/shell.py
DebugLibrary/sourcelines.py
DebugLibrary/steplistener.py
DebugLibrary/styles.py
DebugLibrary/version.py
DebugLibrary/webdriver.py
robotframework_debuglibrary-2.5.0.dist-info/LICENSE
robotframework_debuglibrary-2.5.0.dist-info/METADATA
robotframework_debuglibrary-2.5.0.dist-info/WHEEL
robotframework_debuglibrary-2.5.0.dist-info/entry_points.txt
robotframework_debuglibrary-2.5.0.dist-info/top_level.txt
robotframework_debuglibrary-2.5.0.dist-info/RECORD
