Metadata-Version: 2.1
Name: robotframework-debuglibrary
Version: 2.5.0
Summary: RobotFramework debug library and an interactive shell
Home-page: https://github.com/xyb/robotframework-debuglibrary/
Author: Xie Yanbo
Author-email: xieyanbo@gmail.com
License: New BSD
Keywords: robotframework,debug,shell,repl
Platform: Linux
Platform: Unix
Platform: Windows
Platform: MacOS X
Classifier: Environment :: Console
Classifier: Development Status :: 5 - Production/Stable
Classifier: License :: OSI Approved :: BSD License
Classifier: Natural Language :: English
Classifier: Operating System :: OS Independent
Classifier: Programming Language :: Python
Classifier: Programming Language :: Python :: 3 :: Only
Classifier: Programming Language :: Python :: 3.8
Classifier: Programming Language :: Python :: 3.9
Classifier: Programming Language :: Python :: 3.10
Classifier: Programming Language :: Python :: 3.11
Classifier: Programming Language :: Python :: 3.12
Classifier: Topic :: Utilities
License-File: LICENSE
Requires-Dist: prompt-toolkit >=3
Requires-Dist: robotframework >=4
